iris/__init__.py
iris/iris.py
iris_tod-2.0.dist-info/METADATA
iris_tod-2.0.dist-info/WHEEL
iris_tod-2.0.dist-info/entry_points.txt
iris_tod-2.0.dist-info/RECORD
