Metadata-Version: 2.4
Name: iris-tod
Version: 2.0
Summary: A powerful Python-based security tool that analyzes HTTP security headers for websites and automatically generates clickjacking payloads when vulnerabilities are detected.
Project-URL: Homepage, https://github.com/joelindra/Iris
Project-URL: Issues, https://github.com/joelindra/Iris/issues
Author-email: Joel Indra <anonre@anonre.com>
Classifier: License :: OSI Approved :: MIT License
Classifier: Operating System :: OS Independent
Classifier: Programming Language :: Python :: 3
Requires-Python: >=3.7
Requires-Dist: numpy
Requires-Dist: pandas
